Metadata-Version: 1.0
Name: plone.recipe.lxml
Version: 0.4
Summary: Recipe that builds lxml and dependencies (libxslt, libxml2).
Home-page: http://svn.plone.org/svn/collective/buildout/plone.recipe.lxml
Author: Joscha Krutzki
Author-email: joka at jokasis de
License: ZPL 2.1
Keywords: lxml recipe
Platform: UNKNOWN
Classifier: License :: OSI Approved :: Zope Public License
Classifier: Framework :: Buildout
Classifier: Framework :: Plone
Classifier: Framework :: Zope2
Classifier: Programming Language :: Python
Classifier: Topic :: Text Processing :: Markup :: XML
